Metadata-Version: 2.1
Name: gcp-airflow-foundations
Version: 0.3.6
Summary: Opinionated framework based on Airflow 2.0 for building pipelines to ingest data into a BigQuery data warehouse
Home-page: https://github.com/badal-io/gcp-airflow-foundations
Author: Badal.io
Author-email: info@badal.io
License: Apache 2.0
Platform: UNKNOWN
Classifier: Development Status :: 4 - Beta
Classifier: Intended Audience :: Developers
Classifier: Topic :: Software Development :: Libraries
Classifier: License :: OSI Approved :: Apache Software License
Classifier: Programming Language :: Python :: 3.6
Classifier: Programming Language :: Python :: 3.7
Classifier: Programming Language :: Python :: 3.8
Classifier: Programming Language :: Python :: 3.9
Requires-Dist: pydantic (==1.8.2)
Requires-Dist: facebook-business (>=10.0.0)
Requires-Dist: dacite (>=1.5.0)
Requires-Dist: regex (>=2021.11.1)
Requires-Dist: twilio
Requires-Dist: pandas (>=0.17.1)
Requires-Dist: pyarrow (>=3.0.0)
Provides-Extra: providers
Requires-Dist: apache-airflow-providers-salesforce (==5.1.0) ; extra == 'providers'
Requires-Dist: apache-airflow-providers-google (==8.2.0) ; extra == 'providers'
Requires-Dist: apache-airflow-providers-apache-beam (==4.0.0) ; extra == 'providers'
Requires-Dist: apache-airflow-providers-facebook (==3.0.1) ; extra == 'providers'
Provides-Extra: test
Requires-Dist: pytest (==5.3.5) ; extra == 'test'
Requires-Dist: pytest-testconfig (==0.2.0) ; extra == 'test'
Requires-Dist: pytest-airflow (>=0.0.3) ; extra == 'test'
Requires-Dist: pytest-cov (==3.0.0) ; extra == 'test'
Requires-Dist: flake8 (==4.0.1) ; extra == 'test'
